[
    {
        "name": "id",
        "dbType": "integer,true",
        "htmlType": null,
        "validations": null,
        "searchable": false,
        "fillable": false,
        "primary": true,
        "inForm": false,
        "inIndex": false
    },
    {
        "name": "Description",
        "dbType": "string",
        "htmlType": "text",
        "validations": null,
        "searchable": true,
        "fillable": true,
        "primary": false,
        "inForm": true,
        "inIndex": true
    },
    {
        "name": "idMovementType",
        "dbType": "integer,false",
        "htmlType": null,
        "validations": "required",
        "searchable": true,
        "fillable": true,
        "primary": false,
        "inForm": true,
        "inIndex": true
    },
    {
        "name": "idUserReceives",
        "dbType": "integer,false",
        "htmlType": null,
        "validations": "required",
        "searchable": true,
        "fillable": true,
        "primary": false,
        "inForm": true,
        "inIndex": true
    },
    {
        "name": "idUserSends",
        "dbType": "integer,false",
        "htmlType": null,
        "validations": "required",
        "searchable": true,
        "fillable": true,
        "primary": false,
        "inForm": true,
        "inIndex": true
    },
    {
        "name": "idBranchReceives",
        "dbType": "integer,false",
        "htmlType": null,
        "validations": "required",
        "searchable": true,
        "fillable": true,
        "primary": false,
        "inForm": true,
        "inIndex": true
    },
    {
        "name": "idBranchSends",
        "dbType": "integer,false",
        "htmlType": null,
        "validations": "required",
        "searchable": true,
        "fillable": true,
        "primary": false,
        "inForm": true,
        "inIndex": true
    },
    {
        "name": "idTransport",
        "dbType": "integer,false",
        "htmlType": null,
        "validations": "required",
        "searchable": true,
        "fillable": true,
        "primary": false,
        "inForm": true,
        "inIndex": true
    },
    {
        "name": "created_at",
        "dbType": "datetime",
        "htmlType": "date",
        "validations": null,
        "searchable": false,
        "fillable": false,
        "primary": false,
        "inForm": false,
        "inIndex": false
    },
    {
        "name": "updated_at",
        "dbType": "datetime",
        "htmlType": "date",
        "validations": null,
        "searchable": false,
        "fillable": false,
        "primary": false,
        "inForm": false,
        "inIndex": false
    },
    {
        "name": "deleted_at",
        "dbType": "datetime",
        "htmlType": "date",
        "validations": null,
        "searchable": false,
        "fillable": false,
        "primary": false,
        "inForm": false,
        "inIndex": false
    },
    {
        "type": "relation",
        "relation": "mt1,Branch,idBranchReceives"
    },
    {
        "type": "relation",
        "relation": "mt1,Branch,idBranchSends"
    },
    {
        "type": "relation",
        "relation": "mt1,Movementtype,idMovementType"
    },
    {
        "type": "relation",
        "relation": "mt1,Transport,idTransport"
    },
    {
        "type": "relation",
        "relation": "mt1,User,idUserReceives"
    },
    {
        "type": "relation",
        "relation": "mt1,User,idUserSends"
    },
    {
        "type": "relation",
        "relation": "1tm,Transferd"
    }
]